MAPF/MAPF.py
MAPF-0.9.9.dist-info/DESCRIPTION.rst
MAPF-0.9.9.dist-info/METADATA
MAPF-0.9.9.dist-info/RECORD
MAPF-0.9.9.dist-info/WHEEL
MAPF-0.9.9.dist-info/metadata.json
MAPF-0.9.9.dist-info/top_level.txt
